stack_overflow_mcp_light/__init__.py
stack_overflow_mcp_light/logging_config.py
stack_overflow_mcp_light/server.py
stack_overflow_mcp_light/models/__init__.py
stack_overflow_mcp_light/models/requests.py
stack_overflow_mcp_light/models/responses.py
stack_overflow_mcp_light/tools/__init__.py
stack_overflow_mcp_light/tools/base_client.py
stack_overflow_mcp_light/tools/questions.py
stack_overflow_mcp_light-1.2.0.dist-info/METADATA
stack_overflow_mcp_light-1.2.0.dist-info/WHEEL
stack_overflow_mcp_light-1.2.0.dist-info/entry_points.txt
stack_overflow_mcp_light-1.2.0.dist-info/licenses/LICENSE
stack_overflow_mcp_light-1.2.0.dist-info/RECORD
