Metadata-Version: 2.4
Name: stack-overflow-mcp-light
Version: 1.2.0
Summary: A server that exposes a set of tools for interacting with Stack Overflow API. It provides functionality for searching questions, answers, tags, and retrieving detailed information from Stack Overflow.
Project-URL: Homepage, https://github.com/midodimori/stack-overflow-mcp-light
Project-URL: Repository, https://github.com/midodimori/stack-overflow-mcp-light
Project-URL: Issues, https://github.com/midodimori/stack-overflow-mcp-light/issues
Project-URL: Documentation, https://github.com/midodimori/stack-overflow-mcp-light#readme
Author-email: Minh DOAN <nhatminhdoan2702@gmail.com>
License: MIT License
License-File: LICENSE
Keywords: answers,api,mcp,questions,search,stackoverflow
Classifier: Development Status :: 4 - Beta
Classifier: Intended Audience :: Developers
Classifier: License :: OSI Approved :: MIT License
Classifier: Operating System :: OS Independent
Classifier: Programming Language :: Python :: 3
Classifier: Programming Language :: Python :: 3.13
Classifier: Topic :: Internet :: WWW/HTTP :: Dynamic Content
Classifier: Topic :: Software Development :: Libraries :: Python Modules
Requires-Python: >=3.11
Requires-Dist: fastmcp>=2.10.6
Requires-Dist: httpx>=0.27.0
Requires-Dist: pydantic>=2.11.7
Requires-Dist: python-dotenv>=1.1.1
Provides-Extra: dev
Requires-Dist: black>=25.1.0; extra == 'dev'
Requires-Dist: isort>=6.0.1; extra == 'dev'
Requires-Dist: mcp[cli]>=1.12.2; extra == 'dev'
Requires-Dist: mypy>=1.17.0; extra == 'dev'
Requires-Dist: pytest-asyncio>=1.1.0; extra == 'dev'
Requires-Dist: pytest-cov>=6.0.0; extra == 'dev'
Requires-Dist: pytest-mock>=3.14.1; extra == 'dev'
Requires-Dist: pytest>=8.4.1; extra == 'dev'
Requires-Dist: python-dotenv>=1.1.1; extra == 'dev'
Requires-Dist: ruff>=0.12.5; extra == 'dev'
